.travis.yml
CHANGES.txt
LICENSE.txt
Makefile
README.md
README.rst
README.txt
setup.py
version.txt
docs/Makefile
docs/make.bat
docs/source/conf.py
docs/source/index.rst
docs/source/_templates/indexsidebar.html
docs/source/_themes/bootstrap.zip
grape/__init__.py
grape.recipe.pipeline.egg-info/PKG-INFO
grape.recipe.pipeline.egg-info/SOURCES.txt
grape.recipe.pipeline.egg-info/dependency_links.txt
grape.recipe.pipeline.egg-info/entry_points.txt
grape.recipe.pipeline.egg-info/namespace_packages.txt
grape.recipe.pipeline.egg-info/not-zip-safe
grape.recipe.pipeline.egg-info/requires.txt
grape.recipe.pipeline.egg-info/top_level.txt
grape/recipe/__init__.py
grape/recipe/pipeline/__init__.py
grape/recipe/pipeline/prepare.py
grape/recipe/pipeline/tests/README.txt
grape/recipe/pipeline/tests/__init__.py
grape/recipe/pipeline/tests/test_prepare.py